caurus/__init__.py
caurus/barcode.py
caurus/cli.py
caurus/server.py
caurus-0.1.0.dist-info/LICENSE
caurus-0.1.0.dist-info/METADATA
caurus-0.1.0.dist-info/WHEEL
caurus-0.1.0.dist-info/entry_points.txt
caurus-0.1.0.dist-info/top_level.txt
caurus-0.1.0.dist-info/RECORD
