Metadata-Version: 2.1
Name: caurus
Version: 0.1.0
Summary: verification scheme based on 2D barcodes
Home-page: http://github.com/george-hopkins/caurus
Author: George Hopkins
Author-email: george-hopkins@null.net
License: MIT
Keywords: barcode mfa tfa verification
Platform: UNKNOWN
Classifier: Development Status :: 3 - Alpha
Classifier: License :: OSI Approved :: MIT License
Classifier: Programming Language :: Python :: 3.5
Classifier: Programming Language :: Python :: 3.6
Classifier: Programming Language :: Python :: 3.7
Classifier: Topic :: Security
Requires-Dist: bitstring
Requires-Dist: crcmod
Requires-Dist: cryptography
Requires-Dist: svgwrite
Requires-Dist: reedsolo
